{
    "Password and Confirm password is not match!" : "كلمة المرور وتأكيد كلمة المرور غير متطابقين!" ,
    "Password must be at least 6 characters long" : "الرقم السري يجب الا يقل عن 6 احرف على الاقل" ,
    "Password field cannot be left blank" : "لا يمكن ترك حقل كلمة المرور فارغا" ,

    "Name field cannot be left blank" : "لا يمكن ترك حقل الاسم فارغا" ,
    "Phone field cannot be left blank" : "لا يمكن ترك حقل الهاتف فارغا" ,
    "Not Valied Email Address" : "عنوان بريد إلكتروني غير صحيح" ,
    "Email field cannot be left blank" : "لا يمكن ترك حقل الايميل فارغا" ,
    "User Name field cannot be left blank" : "لا يمكن ترك حقل اسم المستخدم فارغا",
    "please enter code you received" : "الرجاء إدخال الرمز اللذي تلقيته" ,
    "CONFIRM" : "تأكيد" ,
    "The contract was successfully signed" : "تم توقيع العقد بنجاح",
    "You must agree to the terms and conditions" : "يجب عليك الموافقه علي الشروط والاحكام",
    "Are you sure you want to logout?" : "هل تود تسجيل الخروج" ,
    "OK" : "نعم" ,
    "cancel" : "إلغاء" ,
    "The Profile was successfully Editted" : "تم تعديل الملف الشخصي بنجاح" ,
    "Change Language" : "تغيير اللغة" ,
    "Help" : "المساعدة" ,
    "Terms & Conditions" : "الشروط والأحكام" ,
    "About US" : "من نحن" ,
    "Our Products" : "أعمالنا" ,
    "Profile" : "الملف الشخصي" ,
    "Notification" : "الإشعارات" ,
    "Projects" : "المشاريع" ,
    "changeLanguage" : "تغيير اللغة" ,
    "changeLanguageMessage" : "تنبيه تغيير اللغة" ,
      "testfox" : "تنبيه تغيير اللغة" ,
    "change" : "تغيير"
}
